pydantic_sqlalchemy_2/__init__.py
pydantic_sqlalchemy_2/main.py
pydantic_sqlalchemy_2-0.0.2.dist-info/LICENSE
pydantic_sqlalchemy_2-0.0.2.dist-info/METADATA
pydantic_sqlalchemy_2-0.0.2.dist-info/WHEEL
pydantic_sqlalchemy_2-0.0.2.dist-info/RECORD
