Metadata-Version: 2.1
Name: pydantic-sqlalchemy-2
Version: 0.0.2
Summary: Tools to convert SQLAlchemy models to Pydantic models. For use with SQLAlchemy 2.0
License: MIT
Author: Eric Richard
Author-email: ehutzle@gmail.com
Requires-Python: >=3.7,<4.0
Classifier: License :: OSI Approved :: MIT License
Classifier: Programming Language :: Python :: 3
Classifier: Programming Language :: Python :: 3.7
Classifier: Programming Language :: Python :: 3.8
Classifier: Programming Language :: Python :: 3.9
Classifier: Programming Language :: Python :: 3.10
Classifier: Programming Language :: Python :: 3.11
Provides-Extra: dev
Requires-Dist: autoflake[dev] (>=1.3.1,<2.0.0) ; extra == "dev"
Requires-Dist: flake8[dev] (>=3.7.9,<4.0.0) ; extra == "dev"
Requires-Dist: jupyter[dev] (>=1.0.0,<2.0.0) ; extra == "dev"
Requires-Dist: pydantic (>=1.5.1,<2.0.0)
Requires-Dist: sqlalchemy (>=2.0.00,<3.0.0)
